[
	{
		"name": "Gates of the Underworld",
		"chest_unopened_img": "/images/Items/close.png",
		"chest_opened_img": "/images/Items/open.png",
		"access_rules": [ "$runestonesCollected" ],
		"children": [
			{
				"name": "Potion Pile",
				"chest_unopened_img": "/images/items/item.png",
				"chest_opened_img": "/images/items/item_obtained.png",
				"sections": [
					{
						"name": "Potion Pile"
					}
				]
			},
			{
				"name": "Rapid Fire (Dif. 3)",
				"chest_unopened_img": "/images/items/item.png",
				"chest_opened_img": "/images/items/item_obtained.png",
				"visibility_rules": [ "$difficulty3Enabled" ],
				"sections": [
					{
						"name": "Rapid Fire (Dif. 3)"
					}
				]
			},
			{
				"name": "Reflective Shield (Dif. 2)",
				"chest_unopened_img": "/images/items/item.png",
				"chest_opened_img": "/images/items/item_obtained.png",
				"visibility_rules": [ "$difficulty2Enabled" ],
				"sections": [
					{
						"name": "Reflective Shield (Dif. 2)"
					}
				]
			},
			{
				"name": "Reflective Shot (Dif. 2)",
				"chest_unopened_img": "/images/items/item.png",
				"chest_opened_img": "/images/items/item_obtained.png",
				"visibility_rules": [ "$difficulty2Enabled" ],
				"sections": [
					{
						"name": "Reflective Shot (Dif. 2)"
					}
				]
			},
			{
				"name": "Lightning Shield (Dif. 2)",
				"chest_unopened_img": "/images/items/item.png",
				"chest_opened_img": "/images/items/item_obtained.png",
				"visibility_rules": [ "$difficulty2Enabled" ],
				"sections": [
					{
						"name": "Lightning Shield (Dif. 2)"
					}
				]
			},
			{
				"name": "Fire Shield (Dif. 3)",
				"chest_unopened_img": "/images/items/item.png",
				"chest_opened_img": "/images/items/item_obtained.png",
				"visibility_rules": [ "$difficulty3Enabled" ],
				"sections": [
					{
						"name": "Fire Shield (Dif. 3)"
					}
				]
			},
			{
				"name": "Acid Amulet (Dif. 4)",
				"chest_unopened_img": "/images/items/item.png",
				"chest_opened_img": "/images/items/item_obtained.png",
				"visibility_rules": [ "$difficulty4Enabled" ],
				"sections": [
					{
						"name": "Acid Amulet (Dif. 4)"
					}
				]
			},
			{
				"name": "Light Amulet (Dif. 3)",
				"chest_unopened_img": "/images/items/item.png",
				"chest_opened_img": "/images/items/item_obtained.png",
				"visibility_rules": [ "$difficulty3Enabled" ],
				"sections": [
					{
						"name": "Light Amulet (Dif. 3)"
					}
				]
			},
			{
				"name": "Lightning Amulet (Dif. 2)",
				"chest_unopened_img": "/images/items/item.png",
				"chest_opened_img": "/images/items/item_obtained.png",
				"visibility_rules": [ "$difficulty2Enabled" ],
				"sections": [
					{
						"name": "Lightning Amulet (Dif. 2)"
					}
				]
			},
			{
				"name": "Fire Amulet",
				"chest_unopened_img": "/images/items/item.png",
				"chest_opened_img": "/images/items/item_obtained.png",
				"sections": [
					{
						"name": "Fire Amulet"
					}
				]
			},
			{
				"name": "Growth",
				"chest_unopened_img": "/images/items/item.png",
				"chest_opened_img": "/images/items/item_obtained.png",
				"sections": [
					{
						"name": "Growth"
					}
				]
			},
			{
				"name": "Fire Breath",
				"chest_unopened_img": "/images/items/item.png",
				"chest_opened_img": "/images/items/item_obtained.png",
				"sections": [
					{
						"name": "Fire Breath"
					}
				]
			},
			{
				"name": "Phoenix Familiar (Dif. 2)",
				"chest_unopened_img": "/images/items/item.png",
				"chest_opened_img": "/images/items/item_obtained.png",
				"visibility_rules": [ "$difficulty2Enabled" ],
				"sections": [
					{
						"name": "Phoenix Familiar (Dif. 2)"
					}
				]
			},
			{
				"name": "Invulnerability (Dif. 4)",
				"chest_unopened_img": "/images/items/item.png",
				"chest_opened_img": "/images/items/item_obtained.png",
				"visibility_rules": [ "$difficulty4Enabled" ],
				"sections": [
					{
						"name": "Invulnerability (Dif. 4)"
					}
				]
			},
			{
				"name": "Acid Breath (Dif. 3)",
				"chest_unopened_img": "/images/items/item.png",
				"chest_opened_img": "/images/items/item_obtained.png",
				"visibility_rules": [ "$difficulty3Enabled" ],
				"sections": [
					{
						"name": "Acid Breath (Dif. 3)"
					}
				]
			},
			{
				"name": "5-Way Shot",
				"chest_unopened_img": "/images/items/item.png",
				"chest_opened_img": "/images/items/item_obtained.png",
				"sections": [
					{
						"name": "5-Way Shot"
					}
				]
			},
			{
				"name": "Thunder Hammer (Dif. 4)",
				"chest_unopened_img": "/images/items/item.png",
				"chest_opened_img": "/images/items/item_obtained.png",
				"visibility_rules": [ "$difficulty4Enabled" ],
				"sections": [
					{
						"name": "Thunder Hammer (Dif. 4)"
					}
				]
			},
			{
				"name": "Lightning Breath (Dif. 2)",
				"chest_unopened_img": "/images/items/item.png",
				"chest_opened_img": "/images/items/item_obtained.png",
				"visibility_rules": [ "$difficulty2Enabled" ],
				"sections": [
					{
						"name": "Lightning Breath (Dif. 2)"
					}
				]
			},
			{
				"name": "Timestop",
				"chest_unopened_img": "/images/items/item.png",
				"chest_opened_img": "/images/items/item_obtained.png",
				"sections": [
					{
						"name": "Timestop"
					}
				]
			},
			{
				"name": "3-Way Shot (Dif. 4)",
				"chest_unopened_img": "/images/items/item.png",
				"chest_opened_img": "/images/items/item_obtained.png",
				"visibility_rules": [ "$difficulty4Enabled" ],
				"sections": [
					{
						"name": "3-Way Shot (Dif. 4)"
					}
				]
			},
			{
				"name": "Super Shot",
				"chest_unopened_img": "/images/items/item.png",
				"chest_opened_img": "/images/items/item_obtained.png",
				"sections": [
					{
						"name": "Super Shot"
					}
				]
			},
			{
				"name": "Speed Boots (Dif. 3)",
				"chest_unopened_img": "/images/items/item.png",
				"chest_opened_img": "/images/items/item_obtained.png",
				"visibility_rules": [ "$difficulty3Enabled" ],
				"sections": [
					{
						"name": "Speed Boots (Dif. 3)"
					}
				]
			},
			{
				"name": "Shrink (Dif. 4)",
				"chest_unopened_img": "/images/items/item.png",
				"chest_opened_img": "/images/items/item_obtained.png",
				"visibility_rules": [ "$difficulty4Enabled" ],
				"sections": [
					{
						"name": "Shrink (Dif. 4)"
					}
				]
			}
		]
	}
]
